SPI_Slave_Interface/single_port_async_ram.v
module single_port_async_ram
    #(
         parameter MEM_DEPTH = 256,
         parameter ADDR_SIZE = 8,
         parameter INPUT_SIZE = 10,
         parameter WORD_SIZE = 8
     )
     (
         input wire [INPUT_SIZE-1:0] din,    // Data input most 2 significant bits defines the operation
         /**
          * # din[9:8] Operation (most 2 significant bits)
          * ? Write operation:
          * * 00: Hold din as write address
          * * 01: Write din as data in write address
          * ? Read operation:
          * * 10: Hold din as read address
          * * 11: Read data from read address and tx_valid should be HIGH

          * ? Note that the most significant bit determines the operation if read or write.
         */

         input wire clk,                    // Clock
         input wire rst_n,                  // Active low synchronous reset
         input wire rx_valid,               // If HIGH: accept din to save address or write memory
         output reg [WORD_SIZE-1:0] dout,   // Data output
         output reg tx_valid                // Becomes HIGH when data is ready to be read
     );

    // Memory
    reg [WORD_SIZE-1:0] mem [0:MEM_DEPTH-1];

    // Address registers
    reg [ADDR_SIZE-1:0] addr_wr_reg;
    reg [ADDR_SIZE-1:0] addr_rd_reg;

    always @(posedge clk) begin
        if (~rst_n) begin
            addr_wr_reg <= 0;
            addr_rd_reg <= 0;
            dout <= 0;
            tx_valid <= 0;
        end else begin
            if(rx_valid)  // If rx_valid is HIGH, then do the operation
            begin
                case (din[INPUT_SIZE-1:INPUT_SIZE-2])
                    2'b00: begin
                        addr_wr_reg <= din[WORD_SIZE-1:0];
                        tx_valid <= 0;
                    end
                    2'b01: begin
                        mem[addr_wr_reg] <= din[WORD_SIZE-1:0];
                        tx_valid <= 0;
                    end
                    2'b10: begin
                        addr_rd_reg <= din[WORD_SIZE-1:0];
                        tx_valid <= 0;
                    end
                    2'b11: begin
                        dout <= mem[addr_rd_reg];
                        tx_valid <= 1;
                    end
                endcase
            end
        end
    end

endmodule

SPI_Slave_Interface/single_port_async_ram_tb.v
module single_port_async_ram_tb;

    // Parameters
    parameter MEM_DEPTH = 256;
    parameter ADDR_SIZE = 8;
    parameter INPUT_SIZE = 10;
    parameter WORD_SIZE = 8;

    // Signals
    reg [INPUT_SIZE-1:0] din;
    reg clk;
    reg rst_n;
    reg rx_valid;
    wire [WORD_SIZE-1:0] dout;
    wire tx_valid;

    // Instantiate the DUT (Device Under Test)
    single_port_async_ram #(
                              .MEM_DEPTH(MEM_DEPTH),
                              .ADDR_SIZE(ADDR_SIZE),
                              .INPUT_SIZE(INPUT_SIZE),
                              .WORD_SIZE(WORD_SIZE)
                          ) dut (
                              .din(din),
                              .clk(clk),
                              .rst_n(rst_n),
                              .rx_valid(rx_valid),
                              .dout(dout),
                              .tx_valid(tx_valid)
                          );

    // Clock generation
    initial begin
        clk = 0;
        forever #5 clk = ~clk;
    end

    // Test sequence
    initial begin
        // Initialize signals
        rst_n = 0;
        din = 0;
        rx_valid = 0;

        // Reset the DUT
        #10;
        rst_n = 1;

        // Write address 0x01
        #10;
        din = 10'b0000000001; // Write address 0x01
        rx_valid = 1;
        #10;
        rx_valid = 0;

        // Write data 0xAA to address 0x01
        #10;
        din = 10'b0100001010; // Write data 0x0A
        rx_valid = 1;
        #10;
        rx_valid = 0;

        // Read address 0x01
        #10;
        din = 10'b1000000001; // Read address 0x01
        rx_valid = 1;
        #10;
        rx_valid = 0;

        // Read data from address 0x01
        #10;
        din = 10'b1100000000; // Read data
        rx_valid = 1;
        #10;
        rx_valid = 0;

        // Wait for tx_valid to go high and check the output
        #10;
        if (tx_valid && dout == 8'h0A) begin
            $display("Test Passed: Data read correctly from address 0x01");
        end else begin
            $display("Test Failed: Incorrect data read from address 0x01");
        end

        // Finish the simulation
        #10;
        $finish;
    end

endmodule

SPI_Slave_Interface/sim/single_port_async_ram_tb/simulation.vcd
$date
	Tue Mar  4 05:27:44 2025
$end
$version
	QuestaSim Version 2021.1
$end
$timescale
	1ns
$end

$scope module single_port_async_ram_tb $end
$var parameter 32 ! MEM_DEPTH $end
$var parameter 32 " ADDR_SIZE $end
$var parameter 32 # INPUT_SIZE $end
$var parameter 32 $ WORD_SIZE $end
$var reg 10 % din [9:0] $end
$var reg 1 & clk $end
$var reg 1 ' rst_n $end
$var reg 1 ( rx_valid $end
$var wire 1 ) dout [7] $end
$var wire 1 * dout [6] $end
$var wire 1 + dout [5] $end
$var wire 1 , dout [4] $end
$var wire 1 - dout [3] $end
$var wire 1 . dout [2] $end
$var wire 1 / dout [1] $end
$var wire 1 0 dout [0] $end
$var wire 1 1 tx_valid $end

$scope module dut $end
$var parameter 32 2 MEM_DEPTH $end
$var parameter 32 3 ADDR_SIZE $end
$var parameter 32 4 INPUT_SIZE $end
$var parameter 32 5 WORD_SIZE $end
$var wire 1 6 din [9] $end
$var wire 1 7 din [8] $end
$var wire 1 8 din [7] $end
$var wire 1 9 din [6] $end
$var wire 1 : din [5] $end
$var wire 1 ; din [4] $end
$var wire 1 < din [3] $end
$var wire 1 = din [2] $end
$var wire 1 > din [1] $end
$var wire 1 ? din [0] $end
$var wire 1 @ clk $end
$var wire 1 A rst_n $end
$var wire 1 B rx_valid $end
$var reg 8 C dout [7:0] $end
$var reg 1 D tx_valid $end
$var reg 8 E addr_wr_reg [7:0] $end
$var reg 8 F addr_rd_reg [7:0] $end
$upscope $end
$upscope $end
$enddefinitions $end
#0
$dumpvars
b0 %
0&
0'
0(
bx C
xD
bx E
bx F
b100000000 !
b1000 "
b1010 #
b1000 $
b100000000 2
b1000 3
b1010 4
b1000 5
x0
x/
x.
x-
x,
x+
x*
x)
x1
0B
0A
0@
0?
0>
0=
0<
0;
0:
09
08
07
06
$end
#5
1&
1@
b0 E
b0 F
b0 C
0D
00
0/
0.
0-
0,
0+
0*
0)
01
#10
1'
0&
1A
0@
#15
1&
1@
#20
b1 %
1(
0&
1?
1B
0@
#25
1&
1@
b1 E
#30
0(
0&
0B
0@
#35
1&
1@
#40
b100001010 %
1(
0&
0?
1>
1<
17
1B
0@
#45
1&
1@
#50
0(
0&
0B
0@
#55
1&
1@
#60
b1000000001 %
1(
0&
1?
0>
0<
07
16
1B
0@
#65
1&
1@
b1 F
#70
0(
0&
0B
0@
#75
1&
1@
#80
b1100000000 %
1(
0&
0?
17
1B
0@
#85
1&
1@
b1010 C
1D
1/
1-
11
#90
0(
0&
0B
0@
