SPI_Slave_Interface/single_port_async_ram.v
module single_port_async_ram
    #(
         parameter MEM_DEPTH = 256,
         parameter ADDR_SIZE = 8,
         parameter INPUT_SIZE = 10,
         parameter WORD_SIZE = 8
     )
     (
         input wire [INPUT_SIZE-1:0] din,    // Data input most 2 significant bits defines the operation
         /**
          * # din[9:8] Operation (most 2 significant bits)
          * ? Write operation:
          * * 00: Hold din as write address
          * * 01: Write din as data in write address
          * ? Read operation:
          * * 10: Hold din as read address
          * * 11: Read data from read address and tx_valid should be HIGH

          * ? Note that the most significant bit determines the operation if read or write.
         */

         input wire clk,                    // Clock
         input wire rst_n,                  // Active low synchronous reset
         input wire rx_valid,               // If HIGH: accept din to save address or write memory
         output reg [WORD_SIZE-1:0] dout,   // Data output
         output reg tx_valid                // Becomes HIGH when data is ready to be read
     );

    // Memory
    reg [WORD_SIZE-1:0] mem [0:MEM_DEPTH-1];

    // Address registers
    reg [ADDR_SIZE-1:0] addr_wr_reg;
    reg [ADDR_SIZE-1:0] addr_rd_reg;

    always @(posedge clk) begin
        if (~rst_n) begin
            addr_wr_reg <= 0;
            addr_rd_reg <= 0;
            dout <= 0;
            tx_valid <= 0;
        end else begin
            if(rx_valid)  // If rx_valid is HIGH, then do the operation
            begin
                case (din[INPUT_SIZE-1:INPUT_SIZE-2])
                    2'b00: begin
                        addr_wr_reg <= din[WORD_SIZE-1:0];
                        tx_valid <= 0;
                    end
                    2'b01: begin
                        mem[addr_wr_reg] <= din[WORD_SIZE-1:0];
                        tx_valid <= 0;
                    end
                    2'b10: begin
                        addr_rd_reg <= din[WORD_SIZE-1:0];
                        tx_valid <= 0;
                    end
                    2'b11: begin
                        dout <= mem[addr_rd_reg];
                        tx_valid <= 1;
                    end
                endcase
            end
        end
    end

endmodule

SPI_Slave_Interface/spi_slave_interface_2.v
/**
* * This module is for submission of the project, it needs debug core as required
* * but this added an extra not needed clock cycle when reading data because of 
* * vivado negative hold stack which is not even logical but couldn't resolve it
* * so sacrificing the extra clock when debugging only
  */

module spi_slave_interface_2
    #(
         parameter MEM_DEPTH = 256,
         parameter MEM_ADDR_SIZE = 8,
         parameter MEM_INPUT_SIZE = 10,
         parameter MEM_WORD_SIZE = 8
     )
     (
         input wire MOSI,   // Master Out Slave In
         output reg MISO,   // Master In Slave Out
         input wire clk,    // Serial Clock
         input wire SS_n,   // Slave Select
         input wire rst_n   // Active low synchronous reset
     );

    //// ! Ram Signals
    wire tx_valid;                      // Becomes HIGH when data is ready to be read
    wire [MEM_WORD_SIZE-1:0] tx_data;   // Data input from Memory
    reg rx_valid;                       // Becoms HIGH when sending data to Memory
    reg [MEM_INPUT_SIZE-1:0] rx_data;   // Data output to Memory

    //// ! RAM
    single_port_async_ram #(
                              .MEM_DEPTH(MEM_DEPTH),
                              .ADDR_SIZE(MEM_ADDR_SIZE),
                              .INPUT_SIZE(MEM_INPUT_SIZE),
                              .WORD_SIZE(MEM_WORD_SIZE)
                          ) ram (
                              .din(rx_data),
                              .clk(clk),
                              .rst_n(rst_n),
                              .rx_valid(rx_valid),
                              .dout(tx_data),
                              .tx_valid(tx_valid)
                          );

    //// ! SPI Slave Interface

    // States
    localparam IDLE         = 0;    // Idle state
    localparam CHK_CMD      = 1;    // Takes one MOSI input
    localparam WRITE        = 2;    // Writes address/data is being sent to RAM
    localparam READ_ADD     = 3;    // Read address is being sent to RAM
    localparam READ_DATA    = 4;    // Read data is being saved then sent to MISO

    // Registers for current state (cs) and next state (ns)
    (* fsm_encoding = "one_hot" *)
    reg [2:0] cs, ns;

    // Counter to keep track of bits received or transmitted
    reg [4:0] counter;

    // Flag to indicate a read operation
    reg READ_OP;

    // # State Memory: Sequential logic to update the current state
    always @(posedge clk)
    begin
        if(~rst_n)
            cs <= IDLE;  // Reset to IDLE state
        else
            cs <= ns;    // Update to next state
    end

    // # Next State Logic: Combinational logic to determine the next state
    always @(*)
    begin
        if(~rst_n) begin
            ns = IDLE;                      // Reset to IDLE state
        end
        else begin
            case(cs)
                IDLE: begin
                    if(~SS_n)
                        ns = CHK_CMD;       // Move to CHK_CMD state if Slave Select is active
                    else
                        ns = IDLE;          // Remain in IDLE state
                end
                CHK_CMD: begin
                    if(MOSI == 0)
                        ns = WRITE;         // Move to WRITE state if MOSI is 0 (Write operation)
                    else begin
                        if(READ_OP)
                            ns = READ_DATA; // Move to READ_DATA state if READ_OP is set (Address received before)
                        else
                            ns = READ_ADD;  // Move to READ_ADD state otherwise (Address receiveing)
                    end
                end
                WRITE: begin
                    if(SS_n)
                        ns = IDLE;          // Move to IDLE state if Slave Select is inactive
                    else
                        ns = WRITE;         // Remain in WRITE state
                end
                READ_ADD: begin
                    if(SS_n)
                        ns = IDLE;          // Move to IDLE state if Slave Select is inactive
                    else
                        ns = READ_ADD;      // Remain in READ_ADD state
                end
                READ_DATA: begin
                    if(SS_n)
                        ns = IDLE;          // Move to IDLE state if Slave Select is inactive
                    else
                        ns = READ_DATA;     // Remain in READ_DATA state
                end
                default: ns = IDLE;         // Default to IDLE state
            endcase
        end
    end

    // # Output Logic: Sequential logic to generate outputs based on the current state
    always @(posedge clk) begin
        if(~rst_n)begin
            counter <= 4'b0;
            MISO <= 0;
            READ_OP <= 0;
        end
        else begin
            MISO <= 0;                  // Default MISO to 0
            rx_valid <= 0;              // Default rx_valid to 0
            case(cs)
                IDLE: begin
                    // No operation in IDLE state
                end
                CHK_CMD: begin
                    counter <= 0;       // Reset counter in CHK_CMD state
                end
                WRITE: begin
                    if(counter >= 10)
                        rx_valid <= 1;  // Set rx_valid when 10 bits are received
                    else begin
                        rx_data <= {rx_data[MEM_INPUT_SIZE-2:0], MOSI};  // Shift in MOSI data
                        rx_valid <= 0;
                        counter <= counter + 1;
                    end
                end
                READ_ADD: begin
                    READ_OP <= 1;       // Set READ_OP flag as Address is received
                    if(counter >= 10) begin // ! this could be only 9 but for vivado negative hold stack became 10
                        rx_valid <= 1;  // Set rx_valid when 10 bits are received
                    end
                    else begin
                        rx_data <= {rx_data[MEM_INPUT_SIZE-2:0], MOSI};  // Shift in MOSI data
                        rx_valid <= 0;
                        counter <= counter + 1;
                    end
                end
                READ_DATA: begin
                    READ_OP <= 0;       // Clear READ_OP flag as Data is received
                    if(counter >= 18) begin
                        // No operation when counter exceeds 18
                    end
                    else if(counter >= 10) begin
                        rx_valid <= 1;      // Set rx_valid when 10 bits are received
                        if(tx_valid) begin  // If tx_valid is HIGH (Data received from RAM), then send data to MISO
                            counter <= counter + 1;
                            MISO <= tx_data[17-counter];  // Send data on MISO
                        end
                    end
                    else begin
                        rx_data <= {rx_data[MEM_INPUT_SIZE-2:0], MOSI};  // Shift in MOSI data
                        counter <= counter + 1;
                        if(counter >= 10)
                            rx_valid <= 1;  // Set rx_valid when 10 bits are received to pass to RAM
                    end
                end
                default: begin
                    rx_valid <= 0;
                    MISO <= 0;
                    counter <= 0;
                end
            endcase
        end
    end

endmodule

SPI_Slave_Interface/spi_slave_interface_2_tb.v
module spi_slave_interface_2_tb;

    // Parameters
    parameter MEM_DEPTH = 256;
    parameter MEM_ADDR_SIZE = 8;
    parameter MEM_INPUT_SIZE = 10;
    parameter MEM_WORD_SIZE = 8;

    // Signals
    reg MOSI;
    wire MISO;
    reg clk;
    reg SS_n;
    reg rst_n;
    reg [7:0] out;
    reg [7:0] expected;

    // Instantiate the DUT (Device Under Test)
    spi_slave_interface_2 #(
                              .MEM_DEPTH(MEM_DEPTH),
                              .MEM_ADDR_SIZE(MEM_ADDR_SIZE),
                              .MEM_INPUT_SIZE(MEM_INPUT_SIZE),
                              .MEM_WORD_SIZE(MEM_WORD_SIZE)
                          ) dut (
                              .MOSI(MOSI),
                              .MISO(MISO),
                              .clk(clk),
                              .SS_n(SS_n),
                              .rst_n(rst_n)
                          );

    // Clock generation
    initial begin
        clk = 0;
        forever #5 clk = ~clk;
    end

    // Test sequence
    initial begin
        // Initialize signals
        rst_n = 0;
        MOSI = 0;
        SS_n = 1;
        expected = 0;
        out = 0;

        // Reset the DUT
        @(negedge clk);
        rst_n = 1;

        // Write address 0x01
        SS_n = 0;
        send_data(10'b0000000001); // Write address
        SS_n = 1;

        // Write data 0x0A to address 0x01
        @(negedge clk);
        @(negedge clk);
        SS_n = 0;
        send_data(10'b0110001010); // Write data
        expected = 8'b10001010;
        SS_n = 1;

        // Read address 0x01
        @(negedge clk);
        @(negedge clk);
        SS_n = 0;
        send_data(10'b1000000001); // Read address
        SS_n = 1;

        // Read data from address 0x01
        @(negedge clk);
        @(negedge clk);
        SS_n = 0;
        send_data(10'b1100000000); // Read data
        @(negedge clk);
        @(negedge clk);
        get_data();
        SS_n = 1;

        // Check the output
        @(posedge clk);
        if (out == expected) begin
            $display("Test Passed: Data read correctly from address 0x01");
        end else begin
            $display("Test Failed: Incorrect data read from address 0x01 expected %d, got %d", expected, out);
        end

        // Finish the simulation
        @(negedge clk);
        $stop;
    end

    // Task to send data to the DUT
    task send_data(input [9:0] data);
        integer i;
        begin
            @(negedge clk);
            MOSI = data[9];
            @(negedge clk);
            for (i = 9; i >= 0; i = i - 1) begin
                MOSI = data[i];
                @(negedge clk);
            end
            MOSI = 0;
        end
    endtask

    task get_data();
        integer i;
        begin
            for (i = 7; i >= 0; i = i - 1) begin
                @(negedge clk);
                out[i] = MISO;
            end
        end
    endtask

endmodule

SPI_Slave_Interface/sim/spi_slave_interface_2_tb/simulation.vcd
$date
	Fri Mar  7 05:26:59 2025
$end
$version
	QuestaSim Version 2021.1
$end
$timescale
	1ns
$end

$scope module spi_slave_interface_2_tb $end
$var parameter 32 ! MEM_DEPTH $end
$var parameter 32 " MEM_ADDR_SIZE $end
$var parameter 32 # MEM_INPUT_SIZE $end
$var parameter 32 $ MEM_WORD_SIZE $end
$var reg 1 % MOSI $end
$var wire 1 & MISO $end
$var reg 1 ' clk $end
$var reg 1 ( SS_n $end
$var reg 1 ) rst_n $end
$var reg 8 * out [7:0] $end
$var reg 8 + expected [7:0] $end

$scope task send_data $end
$var reg 10 , data [9:0] $end
$var integer 32 - i $end
$upscope $end

$scope task get_data $end
$var integer 32 . i $end
$upscope $end

$scope module dut $end
$var parameter 32 / MEM_DEPTH $end
$var parameter 32 0 MEM_ADDR_SIZE $end
$var parameter 32 1 MEM_INPUT_SIZE $end
$var parameter 32 2 MEM_WORD_SIZE $end
$var parameter 32 3 IDLE $end
$var parameter 32 4 CHK_CMD $end
$var parameter 32 5 WRITE $end
$var parameter 32 6 READ_ADD $end
$var parameter 32 7 READ_DATA $end
$var wire 1 8 MOSI $end
$var reg 1 9 MISO $end
$var wire 1 : clk $end
$var wire 1 ; SS_n $end
$var wire 1 < rst_n $end
$var wire 1 = tx_valid $end
$var wire 1 > tx_data [7] $end
$var wire 1 ? tx_data [6] $end
$var wire 1 @ tx_data [5] $end
$var wire 1 A tx_data [4] $end
$var wire 1 B tx_data [3] $end
$var wire 1 C tx_data [2] $end
$var wire 1 D tx_data [1] $end
$var wire 1 E tx_data [0] $end
$var reg 1 F rx_valid $end
$var reg 10 G rx_data [9:0] $end
$var reg 3 H cs [2:0] $end
$var reg 3 I ns [2:0] $end
$var reg 5 J counter [4:0] $end
$var reg 1 K READ_OP $end

$scope module ram $end
$var parameter 32 L MEM_DEPTH $end
$var parameter 32 M ADDR_SIZE $end
$var parameter 32 N INPUT_SIZE $end
$var parameter 32 O WORD_SIZE $end
$var wire 1 P din [9] $end
$var wire 1 Q din [8] $end
$var wire 1 R din [7] $end
$var wire 1 S din [6] $end
$var wire 1 T din [5] $end
$var wire 1 U din [4] $end
$var wire 1 V din [3] $end
$var wire 1 W din [2] $end
$var wire 1 X din [1] $end
$var wire 1 Y din [0] $end
$var wire 1 : clk $end
$var wire 1 < rst_n $end
$var wire 1 Z rx_valid $end
$var reg 8 [ dout [7:0] $end
$var reg 1 \ tx_valid $end
$var reg 8 ] addr_wr_reg [7:0] $end
$var reg 8 ^ addr_rd_reg [7:0] $end
$upscope $end
$upscope $end
$upscope $end
$enddefinitions $end
#0
$dumpvars
0%
0'
1(
0)
b0 *
b0 +
x9
xF
bx G
bx [
x\
bx ]
bx ^
bx H
b0 I
bx J
xK
bx ,
b100000000 !
b1000 "
b1010 #
b1000 $
b100000000 /
b1000 0
b1010 1
b1000 2
b0 3
b1 4
b10 5
b11 6
b100 7
b100000000 L
b1000 M
b1010 N
b1000 O
bx -
bx .
x&
x=
xE
xD
xC
xB
xA
x@
x?
x>
0<
1;
0:
08
xZ
xY
xX
xW
xV
xU
xT
xS
xR
xQ
xP
$end
#5
1'
1:
b0 ]
b0 ^
b0 [
0\
b0 H
b0 J
09
0K
0E
0D
0C
0B
0A
0@
0?
0>
0=
0&
#10
0'
0:
1)
0(
b1 ,
1<
0;
b1 I
#15
1'
1:
b1 H
0F
0Z
b10 I
#20
0'
0:
#25
1'
1:
b10 H
#30
0'
0:
b1001 -
#35
1'
1:
bx0 G
b1 J
0Y
#40
0'
0:
b1000 -
#45
1'
1:
bx00 G
b10 J
0X
#50
0'
0:
b111 -
#55
1'
1:
bx000 G
b11 J
0W
#60
0'
0:
b110 -
#65
1'
1:
bx0000 G
b100 J
0V
#70
0'
0:
b101 -
#75
1'
1:
bx00000 G
b101 J
0U
#80
0'
0:
b100 -
#85
1'
1:
bx000000 G
b110 J
0T
#90
0'
0:
b11 -
#95
1'
1:
bx0000000 G
b111 J
0S
#100
0'
0:
b10 -
#105
1'
1:
bx00000000 G
b1000 J
0R
#110
0'
0:
b1 -
#115
1'
1:
bx000000000 G
b1001 J
0Q
#120
0'
0:
b0 -
1%
18
#125
1'
1:
b1 G
b1010 J
1Y
0P
#130
0'
0:
b11111111111111111111111111111111 -
#135
1'
1:
1F
1Z
#140
0'
0:
1(
1;
b0 I
#145
1'
1:
b0 H
b1 ]
0F
1F
#150
0'
0:
#155
1'
1:
0F
0Z
#160
0'
0:
0(
b100001010 ,
0;
b1 I
#165
1'
1:
b1 H
b11 I
#170
0'
0:
0%
08
b10 I
#175
1'
1:
b10 H
b0 J
#180
0'
0:
b1001 -
#185
1'
1:
b10 G
b1 J
0Y
1X
#190
0'
0:
b1000 -
1%
18
#195
1'
1:
b101 G
b10 J
1Y
0X
1W
#200
0'
0:
b111 -
0%
08
#205
1'
1:
b1010 G
b11 J
0Y
1X
0W
1V
#210
0'
0:
b110 -
#215
1'
1:
b10100 G
b100 J
0X
1W
0V
1U
#220
0'
0:
b101 -
#225
1'
1:
b101000 G
b101 J
0W
1V
0U
1T
#230
0'
0:
b100 -
#235
1'
1:
b1010000 G
b110 J
0V
1U
0T
1S
#240
0'
0:
b11 -
1%
18
#245
1'
1:
b10100001 G
b111 J
1Y
0U
1T
0S
1R
#250
0'
0:
b10 -
0%
08
#255
1'
1:
b101000010 G
b1000 J
0Y
1X
0T
1S
0R
1Q
#260
0'
0:
b1 -
1%
18
#265
1'
1:
b1010000101 G
b1001 J
1Y
0X
1W
0S
1R
0Q
1P
#270
0'
0:
b0 -
0%
08
#275
1'
1:
b100001010 G
b1010 J
0Y
1X
0W
1V
0R
1Q
0P
#280
0'
0:
b11111111111111111111111111111111 -
b1010 +
#285
1'
1:
1F
1Z
#290
0'
0:
1(
1;
b0 I
#295
1'
1:
b0 H
0F
1F
#300
0'
0:
#305
1'
1:
0F
0Z
#310
0'
0:
0(
b1000000001 ,
0;
b1 I
#315
1'
1:
b1 H
b10 I
#320
0'
0:
1%
18
b11 I
#325
1'
1:
b11 H
b0 J
#330
0'
0:
b1001 -
#335
1'
1:
1K
b1000010101 G
b1 J
1Y
0X
1W
0V
1U
0Q
1P
#340
0'
0:
b1000 -
0%
08
#345
1'
1:
b101010 G
b10 J
0Y
1X
0W
1V
0U
1T
0P
#350
0'
0:
b111 -
#355
1'
1:
b1010100 G
b11 J
0X
1W
0V
1U
0T
1S
#360
0'
0:
b110 -
#365
1'
1:
b10101000 G
b100 J
0W
1V
0U
1T
0S
1R
#370
0'
0:
b101 -
#375
1'
1:
b101010000 G
b101 J
0V
1U
0T
1S
0R
1Q
#380
0'
0:
b100 -
#385
1'
1:
b1010100000 G
b110 J
0U
1T
0S
1R
0Q
1P
#390
0'
0:
b11 -
#395
1'
1:
b101000000 G
b111 J
0T
1S
0R
1Q
0P
#400
0'
0:
b10 -
#405
1'
1:
b1010000000 G
b1000 J
0S
1R
0Q
1P
#410
0'
0:
b1 -
#415
1'
1:
b100000000 G
b1001 J
0R
1Q
0P
#420
0'
0:
b0 -
1%
18
#425
1'
1:
b1000000001 G
b1010 J
1Y
0Q
1P
#430
0'
0:
b11111111111111111111111111111111 -
#435
1'
1:
1F
1Z
#440
0'
0:
1(
1;
b0 I
#445
1'
1:
b0 H
b1 ^
0F
1F
#450
0'
0:
#455
1'
1:
0F
0Z
#460
0'
0:
0(
b1100000000 ,
0;
b1 I
#465
1'
1:
b1 H
b100 I
#470
0'
0:
#475
1'
1:
b100 H
b0 J
#480
0'
0:
b1001 -
#485
1'
1:
0K
b11 G
b1 J
1X
0P
#490
0'
0:
b1000 -
#495
1'
1:
b111 G
b10 J
1W
#500
0'
0:
b111 -
0%
08
#505
1'
1:
b1110 G
b11 J
0Y
1V
#510
0'
0:
b110 -
#515
1'
1:
b11100 G
b100 J
0X
1U
#520
0'
0:
b101 -
#525
1'
1:
b111000 G
b101 J
0W
1T
#530
0'
0:
b100 -
#535
1'
1:
b1110000 G
b110 J
0V
1S
#540
0'
0:
b11 -
#545
1'
1:
b11100000 G
b111 J
0U
1R
#550
0'
0:
b10 -
#555
1'
1:
b111000000 G
b1000 J
0T
1Q
#560
0'
0:
b1 -
#565
1'
1:
b1110000000 G
b1001 J
0S
1P
#570
0'
0:
b0 -
#575
1'
1:
b1100000000 G
b1010 J
0R
#580
0'
0:
b11111111111111111111111111111111 -
#585
1'
1:
1F
1Z
#590
0'
0:
#595
1'
1:
b1010 [
1\
0F
1F
1D
1B
1=
#600
0'
0:
#605
1'
1:
0F
1F
b1011 J
#610
0'
0:
b111 .
#615
1'
1:
0F
1F
b1100 J
#620
0'
0:
b110 .
#625
1'
1:
0F
1F
b1101 J
#630
0'
0:
b101 .
#635
1'
1:
0F
1F
b1110 J
#640
0'
0:
b100 .
#645
1'
1:
0F
1F
b1111 J
19
1&
#650
0'
0:
b11 .
b1000 *
#655
1'
1:
09
0F
1F
b10000 J
0&
#660
0'
0:
b10 .
#665
1'
1:
0F
1F
b10001 J
19
1&
#670
0'
0:
b1 .
b1010 *
#675
1'
1:
09
0F
1F
b10010 J
0&
#680
0'
0:
b0 .
#685
1'
1:
0F
0Z
#690
0'
0:
b11111111111111111111111111111111 .
#695
1'
1:
#700
0'
0:
1(
1;
b0 I
#705
1'
1:
b0 H
